sb2n/__init__.py
sb2n/config.py
sb2n/converter.py
sb2n/exporter.py
sb2n/link_restorer.py
sb2n/main.py
sb2n/migrator.py
sb2n/notion_service.py
sb2n/parser.py
sb2n/scrapbox_service.py
sb2n/models/__init__.py
sb2n/models/blocks.py
sb2n/models/pages.py
sb2n-0.2.0.dist-info/METADATA
sb2n-0.2.0.dist-info/WHEEL
sb2n-0.2.0.dist-info/entry_points.txt
sb2n-0.2.0.dist-info/licenses/LICENSE
sb2n-0.2.0.dist-info/RECORD
