Metadata-Version: 2.4
Name: sb2n
Version: 0.2.0
Summary: Helpfeel Cosense (Scrapbox) to Notion Migration Tool
Project-URL: repository, https://github.com/eggplants/sb2n
Author-email: eggplants <w10776e8w@yahoo.co.jp>
License: MIT
License-File: LICENSE
Keywords: notion,scrapbox
Classifier: Development Status :: 3 - Alpha
Classifier: License :: OSI Approved :: MIT License
Classifier: Programming Language :: Python :: 3 :: Only
Classifier: Programming Language :: Python :: 3.14
Classifier: Typing :: Typed
Requires-Python: <4,>=3.14
Requires-Dist: notion-client>=2.7
Requires-Dist: pydantic>=2.12.5
Requires-Dist: python-dotenv>=1
Requires-Dist: scrapbox-client>=0.1
